aiy_prayer/__init__.py
aiy_prayer/__main__.py
aiy_prayer/main.py
aiy_prayer/utils.py
aiy_prayer/voice_assist.py
aiy_prayer/data/startup.mp3
aiy_prayer-1.0.1.dist-info/LICENSE
aiy_prayer-1.0.1.dist-info/METADATA
aiy_prayer-1.0.1.dist-info/WHEEL
aiy_prayer-1.0.1.dist-info/entry_points.txt
aiy_prayer-1.0.1.dist-info/top_level.txt
aiy_prayer-1.0.1.dist-info/RECORD
