Metadata-Version: 2.1
Name: aiy-prayer
Version: 1.0.1
Summary: AIY optimized Python command line tool that tells when the next Islamic prayer will occur.
Home-page: https://github.com/Nabil-Lahssini/Google-AIY-prayer_assistant
Author: Nabil Lahssini
Author-email: NabilLahssini@gmail.com
License: MIT
Platform: UNKNOWN
Classifier: License :: OSI Approved :: MIT License
Classifier: Programming Language :: Python :: 3
Classifier: Programming Language :: Python :: 3.7
Classifier: Programming Language :: Python :: 3.8
Classifier: Programming Language :: Python :: 3.9
Requires-Dist: prayer-tool
Requires-Dist: pygame
